{
  "source": "xhs",
  "title": "小红书爆款笔记",
  "date": "2026-04-23",
  "period": "morning",
  "period_label": "Morning",
  "generated_at": "2026-04-23T08:01:28.527134+08:00",
  "delivery_status": "success",
  "count": 1,
  "stats": {
    "total": 2617,
    "candidate": 815,
    "selected": 76,
    "expired": 1726
  },
  "notes": [
    {
      "note_id": "69e74e62000000001f0074ec",
      "title": "无标题",
      "content": "手把手\"养龙虾\"盯盘，AI Agent比想象中更容易上手 #Autoclaw  #澳龙  #炒股  #股票  #AI工具",
      "author": "龚希望Hope",
      "author_id": "55d9923b3397db589e101d04",
      "cover_image": "https://sns-na-i6.xhscdn.com/1040g00831v7i4tidia0g414fvs93m784anuui28?imageView2/2/w/608/format/heif/q/56|imageMogr2/strip&redImage/frame/0/enhance/4&ap=5&sc=SRH_PRV&sign=1b1b9f7e8b86f37268a9eaa7f7c1d60c&t=69e8d58b&origin=0",
      "url": "https://www.xiaohongshu.com/explore/69e74e62000000001f0074ec?xsec_token=YBgaXyN4Ywi599pkBz382Ygc84GvP5Eom3dcbqr_bLV6E=&xsec_source=pc_search",
      "note_type": "video",
      "topics": [],
      "published_at": "2026-04-22T11:50:21",
      "likes": 1457,
      "collects": 1046,
      "comments": 25,
      "shares": 180,
      "source_type": "keyword",
      "source_value": "养龙虾",
      "first_seen_at": "2026-04-22 08:02:23",
      "last_checked_at": "2026-04-23 00:00:17"
    }
  ]
}
